{
    "cards": [
        { "number": "PU-01", "type": "Periurbano (Somio - La Providencia)", "url": "https://www.google.com/maps/d/edit?mid=1vIhGs9x8UQULkePTjiAMYCJFuQA_yhs&usp=drive_link"},
        { "number": "PU-02", "type": "Periurbano (Somio - La Providencia)", "url": "https://www.google.com/maps/d/edit?mid=1qnAtRCLPhD3pycg5jcP3LpEcpBZtV7o&usp=drive_link"},
        { "number": "PU-03", "type": "Periurbano (Somio - La Providencia)", "url": "https://www.google.com/maps/d/edit?mid=17sqCu0ZyOXFPtx7FA-pnakmaUac6IKo&usp=drive_link"},
        { "number": "PU-04", "type": "Periurbano (Somio - La Providencia)", "url": "https://www.google.com/maps/d/edit?mid=183NF6FcBWZQBtMk6N4MWuf4LGVBHzuU&usp=drive_link"},
        { "number": "PU-05", "type": "Periurbano (Somio - La Providencia)", "url": "https://www.google.com/maps/d/edit?mid=1kQJr4V3oNZZnKiPsHHzxjw1M3cLQ2dk&usp=drive_link"},
        { "number": "PU-06", "type": "Periurbano (Somio - La Providencia)", "url": "https://www.google.com/maps/d/edit?mid=1WT6aHC01fKBEcf62jiNLQz9VoFtCgpk&usp=drive_link"},
        { "number": "PU-07", "type": "Periurbano (Somio - La Providencia)", "url": "https://www.google.com/maps/d/edit?mid=1UehaFAvoE4xccQ_0dO2Ntr4jRE3pT3w&usp=drive_link"},
        { "number": "PU-08", "type": "Periurbano (Somio - La Providencia)", "url": "https://www.google.com/maps/d/edit?mid=1YFT5ZZCRrMoftoBxABBE4KmuELTgDy4&usp=drive_link"},
        { "number": "PU-09", "type": "Periurbano (Somio - La Providencia)", "url": "https://www.google.com/maps/d/edit?mid=1lyqpcsOB0kavjlPInAV6hVaEEV8cxBk&usp=drive_link"},
        { "number": "PU-10", "type": "Periurbano (Somio - La Providencia)", "url": "https://www.google.com/maps/d/edit?mid=1MFEHAEwxSUuAiOaQ7P_6pIN2wKH22oY&usp=drive_link"},
        { "number": "PU-11", "type": "Periurbano (Somio - La Providencia)", "url": "https://www.google.com/maps/d/edit?mid=1DxlN-hmKU2ayVQRfsUzfU4s3d6llHQ8&usp=drive_link"},
        { "number": "PU-12", "type": "Periurbano (Somio - La Providencia)", "url": "https://www.google.com/maps/d/edit?mid=1iOPVqGaQErNNyUWs5AppEC4F0D_63Kk&usp=drive_link"},
        { "number": "PU-13", "type": "Periurbano (Somio - La Providencia)", "url": "https://www.google.com/maps/d/edit?mid=1RVd3fYKf57ncqIG8Z4z2n9VJycH99cI&usp=drive_link"},
        { "number": "PU-14", "type": "Periurbano (Somio - La Providencia)", "url": "https://www.google.com/maps/d/edit?mid=1Tz967xbAnVw4CeTym16OU5voQ5rJGbk&usp=drive_link"},
        { "number": "PU-15", "type": "Periurbano (Somio - La Providencia)", "url": "https://www.google.com/maps/d/edit?mid=16HE6x2MamU_eyU9bu3oQ1Yq1geLbkP4&usp=drive_link"},
        { "number": "PU-16", "type": "Periurbano (Somio - La Providencia)", "url": "https://www.google.com/maps/d/edit?mid=1LSu58DyaTZSvzar3bGpgovysVjuGkJY&usp=drive_link"},
        { "number": "PU-17", "type": "Periurbano (Somio - La Providencia)", "url": "https://www.google.com/maps/d/edit?mid=163QjHAHreWtpBOLlWL87EHh9otbKP5s&usp=drive_link"},
        { "number": "PU-18", "type": "Periurbano (Somio - La Providencia)", "url": "https://www.google.com/maps/d/edit?mid=1PSIDIFgeNaNgEai3GSBG4lC0qUehewc&usp=drive_link"},
        { "number": "PU-19", "type": "Periurbano (Somio - La Providencia)", "url": "https://www.google.com/maps/d/edit?mid=1bp1IE0gtoSI6z0vUdxjOGAOuMLBON9M&usp=drive_link"},
        { "number": "PU-20", "type": "Periurbano (Somio - La Providencia)", "url": "https://www.google.com/maps/d/edit?mid=12gd1OruCJ9w8ZTuqiGPtFKgsZNz9SHI&usp=drive_link"},
        { "number": "PU-21", "type": "Periurbano (Somio - La Providencia)", "url": "https://www.google.com/maps/d/edit?mid=1bzVLaThI6GS2S7ztNusjfUsWQ9CqHG8&usp=drive_link"},
        { "number": "PU-22", "type": "Periurbano (Somio - La Providencia)", "url": "https://www.google.com/maps/d/edit?mid=1Q_whFFzamvPZk0o04EZSu_yL6YlMzSo&usp=drive_link"},
        { "number": "PU-23", "type": "Periurbano (Somio - La Providencia)", "url": "https://www.google.com/maps/d/edit?mid=1lvAIHncy6njvaGEmFfzsCadEmmhKwrE&usp=drive_link"},
        { "number": "PU-24", "type": "Periurbano (Somio - La Providencia)", "url": "https://www.google.com/maps/d/edit?mid=1jiKKfENv2YzS4V4RsbR3yiMiO6bZSgg&usp=drive_link"},
        { "number": "PU-25", "type": "Periurbano (Somio - La Providencia)", "url": "https://www.google.com/maps/d/edit?mid=1S9yqAJi-u4OhMwLGaUv1cDj1GWC9J-s&usp=drive_link"},
        { "number": "PU-26", "type": "Periurbano (Somio - La Providencia)", "url": "https://www.google.com/maps/d/edit?mid=1RKwuFASD4bRYBSiRkhs6kdtHNg2bu9Q&usp=drive_link"},
        { "number": "PU-27", "type": "Periurbano (Somio - La Providencia)", "url": "https://www.google.com/maps/d/edit?mid=1sUqpFGXagIUdNJ5Fsc8bNAJynp6vc_g&usp=drive_link"},
        { "number": "PU-28", "type": "Periurbano (Somio - La Providencia)", "url": "https://www.google.com/maps/d/edit?mid=1sV_uu6fyZZs5g3bW0xYKQAeDKYuTE6c&usp=drive_link"},
        { "number": "EXT-01", "type": "Extraradio", "url": "https://www.google.com/maps/d/edit?mid=1djQKVF7daElHrDEPeSAAViOLx211JjY&usp=drive_link"},
        { "number": "EXT-02", "type": "Extraradio", "url": "https://www.google.com/maps/d/edit?mid=165bW-pcTdpPAoPCtfPw5Nj7ezK6utIM&usp=drive_link"},
        { "number": "EXT-03", "type": "Extraradio", "url": "https://www.google.com/maps/d/edit?mid=1EiIb7umcDhF-RNCGfl5sEAJtd8LAstE&usp=drive_link"},
        { "number": "EXT-04", "type": "Extraradio", "url": "https://www.google.com/maps/d/edit?mid=1JnGOaMcDw7_7YWl6ro6C7hQ_ufokVAE&usp=drive_link"},
        { "number": "EXT-05", "type": "Extraradio", "url": "https://www.google.com/maps/d/edit?mid=1NcePRnosWjywhSQ7I_fvqxgQZCC0fkM&usp=drive_link"},
        { "number": "EXT-06", "type": "Extraradio", "url": "https://www.google.com/maps/d/edit?mid=1R5PCZzWS_5VX1ry9fWZ__0xDnRAEpXY&usp=drive_link"},
        { "number": "EXT-07", "type": "Extraradio", "url": "https://www.google.com/maps/d/edit?mid=1uBq1Gc8ahqvPquKIDhsPFAKqN97ouTw&usp=drive_link"},
        { "number": "EXT-08", "type": "Extraradio", "url": "https://www.google.com/maps/d/edit?mid=1LXlkHjgyrwbcHwd_lKmsS-3A4xU1R_0&usp=drive_link"},
        { "number": "EXT-09", "type": "Extraradio", "url": "https://www.google.com/maps/d/edit?mid=1VzY2jHzm6mW7NzdGqZ_-xgRetbSViL4&usp=drive_link"},
        { "number": "EXT-10", "type": "Extraradio", "url": "https://www.google.com/maps/d/edit?mid=17uyA0tFoK31Mf9Jo-iBVJF8Z0n4oWwM&usp=drive_link"},
        { "number": "EXT-11", "type": "Extraradio", "url": "https://www.google.com/maps/d/edit?mid=1srlFFk8LWL0jhkJWWuHmeRqUMlAknKU&usp=drive_link"},
        { "number": "EXT-12", "type": "Extraradio", "url": "https://www.google.com/maps/d/edit?mid=1N1Ps08ne_HI5hRNG9-DcY8OMoamQyHc&usp=drive_link"},
        { "number": "EXT-13", "type": "Extraradio", "url": "https://www.google.com/maps/d/edit?mid=1zCjieY2cjQpwRNoYchfUYHBGebaORrY&usp=drive_link"},
        { "number": "EXT-14", "type": "Extraradio", "url": "https://www.google.com/maps/d/edit?mid=1Tg2XjGU8reA9gqeB7AbeF1n6UC1xqTg&usp=drive_link"},
        { "number": "EXT-15", "type": "Extraradio", "url": "https://www.google.com/maps/d/edit?mid=1eENM2vtY33u81mZ6ZwBEFeUga9ykHtI&usp=drive_link"},
        { "number": "EXT-16", "type": "Extraradio", "url": "https://www.google.com/maps/d/edit?mid=1w_ZCKei0bg6g93Hc107ewnjjfthsSXs&usp=drive_link"},
        { "number": "EXT-17", "type": "Extraradio", "url": "https://www.google.com/maps/d/edit?mid=1Zz2IR-ZG4V25uSZkvC4yJhJIJzeGxFI&usp=drive_link"},
        { "number": "EXT-18", "type": "Extraradio", "url": "https://www.google.com/maps/d/edit?mid=14rwKLAoVtlW33Kr20jw36rFnnbTlpdM&usp=drive_link"},
        { "number": "EXT-19", "type": "Extraradio", "url": "https://www.google.com/maps/d/edit?mid=1Psn8AkNibWi4zmMazwZ2SWhJPeswrgg&usp=drive_link"},
        { "number": "EXT-20", "type": "Extraradio", "url": "https://www.google.com/maps/d/edit?mid=1I4XMJ6xIAuhQYF7p0s6qBP5ypCvuqbA&usp=drive_link"},
        { "number": "EXT-21", "type": "Extraradio", "url": "https://www.google.com/maps/d/edit?mid=1-EaNQxfXC7ow7vvE9mqw10Q3bd85o5Y&usp=drive_link"},
        { "number": "EXT-22", "type": "Extraradio", "url": "https://www.google.com/maps/d/edit?mid=1TxZznP3xf_MQzLqYHw8z5IXmPsjU7zc&usp=drive_link"},
        { "number": "EXT-23", "type": "Extraradio", "url": "https://www.google.com/maps/d/edit?mid=1XGj42DkBmmwGR6claG70_sL0XRkXqag&usp=drive_link"},
        { "number": "EXT-24", "type": "Extraradio", "url": "https://www.google.com/maps/d/edit?mid=1u-6yamxC65YBgpN7qDEPXPlwrV97Ln0&usp=drive_link"},
        { "number": "EXT-25", "type": "Extraradio", "url": "https://www.google.com/maps/d/edit?mid=1Vop_QfPXGutp3eFUahPekJYN1RQvC7g&usp=drive_link"},
        { "number": "EXT-26", "type": "Extraradio", "url": "https://www.google.com/maps/d/edit?mid=1UlAUOFJVtTyjtP4XYkp4f6lMwAswVFM&usp=drive_link"},
        { "number": "EXT-27", "type": "Extraradio", "url": "https://www.google.com/maps/d/edit?mid=1R-ehHLz97DY6PE5eunvkje-3P0pOtKE&usp=drive_link"},
        { "number": "EXT-28", "type": "Extraradio", "url": "https://www.google.com/maps/d/edit?mid=1FAztsApR8Bt14HLxTFO-55TK9Q74Hj8&usp=drive_link"},
        { "number": "EXT-29", "type": "Extraradio", "url": "https://www.google.com/maps/d/edit?mid=1miiNJhtCJ8YQjfoMUnf6xqyBdZX9gZU&usp=drive_link"},
        { "number": "EXT-30", "type": "Extraradio", "url": "https://www.google.com/maps/d/edit?mid=1e7rmKIQ3cB-MAbrbkhAY2QBs43tZKbc&usp=drive_link"},
        { "number": "EXT-31", "type": "Extraradio", "url": "https://www.google.com/maps/d/edit?mid=1h8glv_wwRCRcwgY-oQ0VQrUIeGdmLxI&usp=drive_link"},
        { "number": "EXT-32", "type": "Extraradio", "url": "https://www.google.com/maps/d/edit?mid=1vfLYDpxKFOpTkaMY9yvEoTz-_wepr-M&usp=drive_link"}
    ]
}